kbhtcpublicapi/__init__.py
kbhtcpublicapi/api_client.py
kbhtcpublicapi/configuration.py
kbhtcpublicapi/exceptions.py
kbhtcpublicapi/model_utils.py
kbhtcpublicapi/rest.py
kbhtcpublicapi/api/__init__.py
kbhtcpublicapi/api/default_api.py
kbhtcpublicapi/apis/__init__.py
kbhtcpublicapi/model/__init__.py
kbhtcpublicapi/model/get_metadata_response.py
kbhtcpublicapi/model/get_response.py
kbhtcpublicapi/model/post_submit_response.py
kbhtcpublicapi/models/__init__.py
publicapi/__init__.py
publicapi/api_client.py
publicapi/configuration.py
publicapi/exceptions.py
publicapi/model_utils.py
publicapi/rest.py
publicapi/api/__init__.py
publicapi/api/default_api.py
publicapi/apis/__init__.py
publicapi/model/__init__.py
publicapi/model/get_metadata_response.py
publicapi/model/get_response.py
publicapi/model/post_submit_response.py
publicapi/models/__init__.py
kbhtcpublicapi-1.0.0.dist-info/METADATA
kbhtcpublicapi-1.0.0.dist-info/WHEEL
kbhtcpublicapi-1.0.0.dist-info/top_level.txt
kbhtcpublicapi-1.0.0.dist-info/RECORD
